{
    "fluentMethods": true,
    "clientRootFolder": "",
    "relationships": [],
    "fields": [
        {
            "fieldName": "author",
            "fieldType": "String"
        },
        {
            "fieldName": "title",
            "fieldType": "String"
        },
        {
            "fieldName": "isbn",
            "fieldType": "String"
        }
    ],
    "dto": "no",
    "searchEngine": false,
    "service": "serviceClass",
    "entityTableName": "book",
    "databaseType": "mongodb",
    "jpaMetamodelFiltering": false,
    "pagination": "pagination"
}
